tests/__init__.py
tests/test.py
websearch/__init__.py
websearch/__main__.py
websearch/extension.json
websearch/script.py
websearch_python-1.2.2.data/scripts/websearch
websearch_python-1.2.2.dist-info/LICENSE
websearch_python-1.2.2.dist-info/METADATA
websearch_python-1.2.2.dist-info/WHEEL
websearch_python-1.2.2.dist-info/top_level.txt
websearch_python-1.2.2.dist-info/RECORD
