Metadata-Version: 2.1
Name: websearch-python
Version: 1.2.2
Summary: Module allowing you to do various searches for links on the Web
Home-page: https://github.com/iTeam-S/WebSearch
Author: iTeam-$
Author-email: contact@iteam-s.xyz
License: UNKNOWN
Project-URL: Bug Tracker, https://github.com/iTeam-S/WebSearch/issues
Platform: UNKNOWN
Classifier: Programming Language :: Python :: 3
Classifier: License :: OSI Approved :: MIT License
Classifier: Operating System :: OS Independent
Requires-Python: >=3.6
Requires-Dist: BeautifulSoup4
Requires-Dist: requests
Requires-Dist: gevent
Requires-Dist: flask
